[
  {
    "Name": "Desarrollo Web",
    "Organization": "Le Wagon",
    "Tech": "Ruby,SQL,Git,Javascript,HTML,CSS,RoR,Figma",
    "Tags": "Full-stack",
    "Duration (hours)": "",
    "Duration (weeks)": 9,
    "Location": "Madrid",
    "Price": 6500,
    "type": "Full",
    "language": "English",
    "Notes": "",
    "URL": "",
    "Attachments": ""
  },
  {
    "Name": "Desarrollo Web",
    "Organization": "Le Wagon",
    "Tech": "Ruby,SQL,Git,Javascript,HTML,CSS,RoR,Figma",
    "Tags": "Full-stack",
    "Duration (hours)": "",
    "Duration (weeks)": 24,
    "Location": "Remote",
    "Price": 6500,
    "type": "Part-time",
    "language": "English,French",
    "Notes": "",
    "URL": "",
    "Attachments": ""
  },
  {
    "Name": "Ciencia de datos",
    "Organization": "Le Wagon",
    "Tech": "Python,Pandas,NumPy,SQL,MatPlotLib,Machine Learning,Deep Learning,TensorFlow,Keras",
    "Tags": "Data Science",
    "Duration (hours)": "",
    "Duration (weeks)": 24,
    "Location": "Remote",
    "Price": 6900,
    "type": "Part-time",
    "language": "English,French",
    "Notes": "",
    "URL": "",
    "Attachments": ""
  },
  {
    "Name": "Ciencia de Datos",
    "Organization": "Le Wagon",
    "Tech": "Python,Pandas,NumPy,SQL,MatPlotLib,Machine Learning,Deep Learning,TensorFlow,Keras",
    "Tags": "Data Science",
    "Duration (hours)": "",
    "Duration (weeks)": 9,
    "Location": "Madrid",
    "Price": 6900,
    "type": "Full",
    "language": "English",
    "Notes": "",
    "URL": "",
    "Attachments": ""
  },
  {
    "Name": "Data Analytics",
    "Organization": "Ironhack",
    "Tech": "Git,SQL,Python,Machine Learning,Tableau,Pandas",
    "Tags": "Data Science",
    "Duration (hours)": "",
    "Duration (weeks)": "12.0,24.0",
    "Location": "Remote",
    "Price": 7500,
    "type": "Part-time,Full",
    "language": "English",
    "Notes": "",
    "URL": "",
    "Attachments": "Syllabus_Data.pdf (https://dl.airtable.com/.attachments/ccd2942046a77a3b6253e7443f8dfe50/cab864fd/Syllabus_Data.pdf)"
  },
  {
    "Name": "Ciberseguridad",
    "Organization": "Ironhack",
    "Tech": "Networks,Security,Malware,Forensics,Ethical Hacking",
    "Tags": "Cybersecurity",
    "Duration (hours)": "",
    "Duration (weeks)": "12.0,24.0",
    "Location": "Remote",
    "Price": 7500,
    "type": "Full,Part-time",
    "language": "English",
    "Notes": "",
    "URL": "",
    "Attachments": "Syllabus_Cyber.pdf (https://dl.airtable.com/.attachments/ba4164426db13b0a24c967acd1b22551/bf55d89a/Syllabus_Cyber.pdf)"
  },
  {
    "Name": "Desarrollo Web",
    "Organization": "Ironhack",
    "Tech": "HTML,CSS,Javascript,Node.js,Express.js,Handlebars,MongoDB,React",
    "Tags": "Full-stack",
    "Duration (hours)": "",
    "Duration (weeks)": "12.0,24.0",
    "Location": "Remote",
    "Price": 7500,
    "type": "Full,Part-time",
    "language": "English,German",
    "Notes": "",
    "URL": "",
    "Attachments": ""
  },
  {
    "Name": "UX/UI",
    "Organization": "Ironhack",
    "Tech": "HTML,CSS,UX,UI,Sketch",
    "Tags": "UX/UI",
    "Duration (hours)": "",
    "Duration (weeks)": "9.0,24.0",
    "Location": "Remote",
    "Price": 7500,
    "type": "Full,Part-time",
    "language": "English",
    "Notes": "",
    "URL": "https://www.ironhack.com/es/diseno-ux-ui/remoto",
    "Attachments": ""
  },
  {
    "Name": "Full-time Bootcamp",
    "Organization": "Skylab Coders",
    "Tech": "Javascript,HTML,CSS,Jest,React,Git,Redux,Node.js,Express.js,MongoDB,Jasmine,Cypress",
    "Tags": "Full-stack",
    "Duration (hours)": "",
    "Duration (weeks)": 11,
    "Location": "Barcelona,Madrid",
    "Price": 5700,
    "type": "Full",
    "language": "Spanish",
    "Notes": "",
    "URL": "",
    "Attachments": ""
  },
  {
    "Name": "Curso Part-time",
    "Organization": "Skylab Coders",
    "Tech": "Javascript,HTML,CSS,Vanilla,Jasmine,React,SASS,JQuery,Firebase",
    "Tags": "Full-stack",
    "Duration (hours)": "",
    "Duration (weeks)": 13,
    "Location": "Barcelona,Madrid",
    "Price": 5700,
    "type": "Part-time",
    "language": "Spanish",
    "Notes": "",
    "URL": "",
    "Attachments": ""
  },
  {
    "Name": "Desarrollo Web Java",
    "Organization": "Ubiqum",
    "Tech": "Java,HTML,CSS,Javascript,Git,Bootstrap,Springboot",
    "Tags": "Full-stack",
    "Duration (hours)": 800,
    "Duration (weeks)": 5,
    "Location": "Barcelona,Madrid,Remote",
    "Price": "",
    "type": "Full,Part-time",
    "language": "Spanish",
    "Notes": "",
    "URL": "",
    "Attachments": ""
  },
  {
    "Name": "Análisis de datos & Machine Learning",
    "Organization": "Ubiqum",
    "Tech": "R,Python,Machine Learning,AWS,Data Mining",
    "Tags": "Data Science",
    "Duration (hours)": 800,
    "Duration (weeks)": 5,
    "Location": "Barcelona,Madrid,Remote",
    "Price": "",
    "type": "Full,Part-time",
    "language": "Spanish",
    "Notes": "",
    "URL": "",
    "Attachments": ""
  },
  {
    "Name": "Desarrollo Web con Javascript",
    "Organization": "Ubiqum",
    "Tech": "HTML,CSS,Javascript,MongoDB,React,Node.js,Express.js",
    "Tags": "Full-stack",
    "Duration (hours)": "",
    "Duration (weeks)": 3,
    "Location": "Barcelona,Madrid,Remote",
    "Price": "",
    "type": "Full,Part-time",
    "language": "Spanish",
    "Notes": "",
    "URL": "https://ubiqum.com/es/programs/desarrollo-web-con-javascript/",
    "Attachments": ""
  },
  {
    "Name": "Full-stack Developer",
    "Organization": "4Geeks Academy",
    "Tech": "HTML,CSS,React,Javascript,Python,Flask,SQL",
    "Tags": "Full-stack",
    "Duration (hours)": "",
    "Duration (weeks)": 16,
    "Location": "Madrid,Remote",
    "Price": 5499,
    "type": "Full,Part-time",
    "language": "Spanish",
    "Notes": "Tienen un modelo que no pagas nada y cuando encuentres trabajo pagas el 10% de tu sueldo hasta pagar todo",
    "URL": "https://4geeksacademy.com/es/coding-bootcamps/full-stack-part-time?location=madrid-spain&utm_source=google&utm_medium=cpc&utm_campaign=10503661130&utm_content=107538582641&utm_term=4geeks%20academy&gclid=CjwKCAjwpMOIBhBAEiwAy5M6YCJZtdE2OElovzvsik57q-pPP5Q-u3g8VNpRqYhx0yJl5rfzTqBUAhoCs-sQAvD_BwE",
    "Attachments": ""
  },
  {
    "Name": "Software Engineer",
    "Organization": "4Geeks Academy",
    "Tech": "React,Redux,algorithms,Design Patterns,GraphQL,SQL,Machine Learning,Sockets",
    "Tags": "Full-stack",
    "Duration (hours)": "",
    "Duration (weeks)": 16,
    "Location": "Madrid",
    "Price": "",
    "type": "Part-time",
    "language": "Spanish",
    "Notes": "Mas avanzado. Es como la segunda parte del bootcamp de Full.stack",
    "URL": "",
    "Attachments": ""
  },
  {
    "Name": "AI/Machine Learning Engineering",
    "Organization": "4Geeks Academy",
    "Tech": "Python,algorithms,NumPy,Pandas,MatPlotLib,SQL,Web Scraping,Machine Learning,AWS",
    "Tags": "Data Science",
    "Duration (hours)": "",
    "Duration (weeks)": 15,
    "Location": "Madrid",
    "Price": "",
    "type": "Part-time",
    "language": "Spanish",
    "Notes": "",
    "URL": "https://4geeksacademy.com/es/coding-bootcamps/curso-inteligencia-artificial",
    "Attachments": ""
  },
  {
    "Name": "Programación web",
    "Organization": "Hack a boss",
    "Tech": "Git,HTML,CSS,Javascript,MySQL,React,Node.js",
    "Tags": "Full-stack",
    "Duration (hours)": "",
    "Duration (weeks)": 16,
    "Location": "Vigo,Coruña,Remote",
    "Price": 6490,
    "type": "Part-time",
    "language": "Spanish",
    "Notes": "",
    "URL": "https://www.hackaboss.com/cursos-programacion",
    "Attachments": ""
  },
  {
    "Name": "Full Stack Jr - Aprende a programar desde cero",
    "Organization": "Keep Coding Tech School",
    "Tech": "Python,Javascript,HTML,CSS,Flask,SQL,Git,AWS",
    "Tags": "Full-stack",
    "Duration (hours)": "",
    "Duration (weeks)": "16,8",
    "Location": "Remote",
    "Price": 4000,
    "type": "Part-time,Full",
    "language": "Spanish",
    "Notes": "",
    "URL": "",
    "Attachments": ""
  },
  {
    "Name": "Desarrollo Web Full Stack",
    "Organization": "Keep Coding Tech School",
    "Tech": "Javascript,HTML,Node.js,React,Linux,Python,Django,Git",
    "Tags": "Full-stack",
    "Duration (hours)": "",
    "Duration (weeks)": 32,
    "Location": "Remote",
    "Price": 6000,
    "type": "Part-time",
    "language": "Spanish",
    "Notes": "",
    "URL": "https://keepcoding.io/nuestros-bootcamps/full-stack-web-bootcamp/#1615545527875-a461819e-68f3",
    "Attachments": ""
  },
  {
    "Name": "Desarrollo de Apps Móviles",
    "Organization": "Keep Coding Tech School",
    "Tech": "Swift,Kotlin,SQL,MySQL,Linux,iOS,Firebase,Android,React Native,Flutter",
    "Tags": "Mobile",
    "Duration (hours)": "",
    "Duration (weeks)": 40,
    "Location": "Remote",
    "Price": 6000,
    "type": "Part-time",
    "language": "Spanish",
    "Notes": "",
    "URL": "https://keepcoding.io/nuestros-bootcamps/full-stack-mobile-bootcamp/",
    "Attachments": ""
  },
  {
    "Name": "Big Data, Inteligencia Artificial & Machine Learning",
    "Organization": "Keep Coding Tech School",
    "Tech": "DataWarehouse,SQL,BigData,Spark,Scala,Data Visualization,D3.js,algorithms,Data Mining,Machine Learning,Deep Learning,NLP",
    "Tags": "Data Science,Data Engineer",
    "Duration (hours)": "",
    "Duration (weeks)": 36,
    "Location": "Remote",
    "Price": 6000,
    "type": "Part-time",
    "language": "Spanish",
    "Notes": "",
    "URL": "https://keepcoding.io/nuestros-bootcamps/full-stack-big-data-machine-learning-bootcamp/",
    "Attachments": ""
  },
  {
    "Name": "DevOps & Cloud Computing",
    "Organization": "Keep Coding Tech School",
    "Tech": "Docker,Linux,Python,Cloud,Kubernetes,GCP,AWS,CI/CD,Networks,Azure",
    "Tags": "SRE",
    "Duration (hours)": "",
    "Duration (weeks)": 24,
    "Location": "Remote",
    "Price": 6000,
    "type": "Part-time",
    "language": "Spanish",
    "Notes": "",
    "URL": "",
    "Attachments": ""
  },
  {
    "Name": "Ciberseguridad",
    "Organization": "Keep Coding Tech School",
    "Tech": "Networks,Linux,Python,Docker,Security,Malware,Crytography,Pentesting,Blue Team,Digital Forensics,Red Team",
    "Tags": "Cybersecurity",
    "Duration (hours)": "",
    "Duration (weeks)": 28,
    "Location": "Remote",
    "Price": 6000,
    "type": "Part-time",
    "language": "Spanish",
    "Notes": "",
    "URL": "https://keepcoding.io/nuestros-bootcamps/bootcamp-en-ciberseguridad/#1616512253023-5a2c0fd9-40bb",
    "Attachments": ""
  },
  {
    "Name": "Máster Bootcamp en Programación y tecnologías Exponenciales",
    "Organization": "Keep Coding Tech School",
    "Tech": "BigData,Machine Learning,AI,DevOps,BlockChain,Git,Python,Node.js,Express.js,MongoDB,React,Redux,AWS,Docker,Flutter,Swift,Kotlin,Firebase,TDD,Cybersecurity",
    "Tags": "CTO",
    "Duration (hours)": "",
    "Duration (weeks)": 48,
    "Location": "Remote",
    "Price": "",
    "type": "Part-time",
    "language": "Spanish",
    "Notes": "",
    "URL": "",
    "Attachments": ""
  },
  {
    "Name": "Marketing digital y Análisis de Datos",
    "Organization": "Keep Coding Tech School",
    "Tech": "Data Analysis,HTML,CSS,Wordpress,Scratch,UX,Branding,SEO,SEM,PPC,Ads,Ecommerce,Google Analytics,Growth Hacking,Tableau,Google Data Studio",
    "Tags": "Digital Marketing",
    "Duration (hours)": "",
    "Duration (weeks)": 24,
    "Location": "Remote",
    "Price": 6000,
    "type": "Part-time",
    "language": "Spanish",
    "Notes": "",
    "URL": "https://keepcoding.io/nuestros-bootcamps/marketing-digital-y-analisis-de-datos/#1614081853633-04631b0b-b027",
    "Attachments": ""
  },
  {
    "Name": "UX/UI Bootcamp",
    "Organization": "UXER School",
    "Tech": "UX,UI,User Testing,Design Systems",
    "Tags": "UX/UI",
    "Duration (hours)": "",
    "Duration (weeks)": 13,
    "Location": "Madrid",
    "Price": 7000,
    "type": "Full",
    "language": "Spanish",
    "Notes": "",
    "URL": "",
    "Attachments": ""
  },
  {
    "Name": "UX/UI Bootcamp",
    "Organization": "UXER School",
    "Tech": "UX,UI,User Testing,Design Systems",
    "Tags": "UX/UI",
    "Duration (hours)": "",
    "Duration (weeks)": 12,
    "Location": "Remote",
    "Price": 5900,
    "type": "Full",
    "language": "Spanish",
    "Notes": "",
    "URL": "",
    "Attachments": ""
  },
  {
    "Name": "UX/UI Bootcamp",
    "Organization": "UXER School",
    "Tech": "UX,UI,User Testing,Design Systems",
    "Tags": "UX/UI",
    "Duration (hours)": "",
    "Duration (weeks)": 15,
    "Location": "Madrid",
    "Price": 4500,
    "type": "Part-time",
    "language": "Spanish",
    "Notes": "",
    "URL": "",
    "Attachments": ""
  },
  {
    "Name": "UX/UI Bootcamp",
    "Organization": "UXER School",
    "Tech": "UX,UI,User Testing,Design Systems",
    "Tags": "UX/UI",
    "Duration (hours)": "",
    "Duration (weeks)": 15,
    "Location": "Remote",
    "Price": 3900,
    "type": "Part-time",
    "language": "Spanish",
    "Notes": "",
    "URL": "",
    "Attachments": ""
  },
  {
    "Name": "Desarrollo Android",
    "Organization": "Architect Coders",
    "Tech": "Android,Git,SOLID,Design Patterns,Pentesting",
    "Tags": "Mobile",
    "Duration (hours)": "",
    "Duration (weeks)": 12,
    "Location": "Remote",
    "Price": "",
    "type": "Part-time",
    "language": "Spanish",
    "Notes": "",
    "URL": "https://architectcoders.com/",
    "Attachments": ""
  },
  {
    "Name": "Javascript React",
    "Organization": "Coders Lab",
    "Tech": "HTML,CSS,SASS,React,Javascript",
    "Tags": "Frontend",
    "Duration (hours)": "",
    "Duration (weeks)": 12,
    "Location": "Madrid",
    "Price": "",
    "type": "Full",
    "language": "Spanish",
    "Notes": "",
    "URL": "",
    "Attachments": ""
  },
  {
    "Name": "Desarrollo Web con Java",
    "Organization": "Ubiqum",
    "Tech": "Java,HTML,CSS,Javascript,Vue,React,Bootstrap,Firebase,Git,Springboot",
    "Tags": "backend,Frontend",
    "Duration (hours)": "",
    "Duration (weeks)": 20,
    "Location": "Madrid,Barcelona",
    "Price": "",
    "type": "Full,Part-time",
    "language": "Spanish",
    "Notes": "",
    "URL": "",
    "Attachments": ""
  },
  {
    "Name": "Análisis de datos & Machine Learning",
    "Organization": "Ubiqum",
    "Tech": "Machine Learning,Python,R,BigData",
    "Tags": "Data Science",
    "Duration (hours)": "",
    "Duration (weeks)": 20,
    "Location": "Madrid,Barcelona",
    "Price": "",
    "type": "Full,Part-time",
    "language": "Spanish",
    "Notes": "",
    "URL": "https://ubiqum.com/es/programs/data-analytics-y-machine-learning/",
    "Attachments": ""
  },
  {
    "Name": "Desarrollo Web con Javascript",
    "Organization": "Ubiqum",
    "Tech": "HTML,CSS,Javascript,Vue,Bootstrap,MongoDB,Express.js,React,Node.js",
    "Tags": "Frontend,backend",
    "Duration (hours)": "",
    "Duration (weeks)": 12,
    "Location": "Madrid,Barcelona",
    "Price": "",
    "type": "Full,Part-time",
    "language": "Spanish",
    "Notes": "",
    "URL": "https://ubiqum.com/es/programs/desarrollo-web-con-javascript/",
    "Attachments": ""
  },
  {
    "Name": "Ciberseguridad",
    "Organization": "The Bridge",
    "Tech": "Red Team,Pentesting,Blue Team",
    "Tags": "Cybersecurity",
    "Duration (hours)": "",
    "Duration (weeks)": "16,32",
    "Location": "Madrid,Remote",
    "Price": 7000,
    "type": "Full,Part-time",
    "language": "Spanish",
    "Notes": "",
    "URL": "",
    "Attachments": "Folleto Bootcamp CIB 20Jul2021.pdf (https://dl.airtable.com/.attachments/10ebb2ca1092513cec6aeadbf9f065c8/522968f8/FolletoBootcampCIB20Jul2021.pdf)"
  },
  {
    "Name": "Data Science",
    "Organization": "The Bridge",
    "Tech": "Python,Data Analysis,Machine Learning,MatPlotLib,algorithms,Deep Learning,AWS,Docker,Spark,Tableau,Shiny,Bokeh,Dash",
    "Tags": "Data Science",
    "Duration (hours)": "",
    "Duration (weeks)": "16,32",
    "Location": "Madrid,Remote",
    "Price": 7000,
    "type": "Full,Part-time",
    "language": "Spanish",
    "Notes": "",
    "URL": "https://www.thebridge.tech/bootcamps/bootcamp-data-science",
    "Attachments": "Folleto Bootcamp DS 20Jul2021.pdf (https://dl.airtable.com/.attachments/df41a9ac20cb0cfcaa5cde931cdecbfd/ae6be5c0/FolletoBootcampDS20Jul2021.pdf)"
  },
  {
    "Name": "Buenas prácticas",
    "Organization": "Craft Code",
    "Tech": "C#,Pentesting,refactoring,Design Patterns,SOLID,Git,DDD,CI/CD",
    "Tags": "backend,best practices",
    "Duration (hours)": "",
    "Duration (weeks)": 16,
    "Location": "Remote",
    "Price": 4000,
    "type": "Part-time",
    "language": "Spanish",
    "Notes": "",
    "URL": "",
    "Attachments": ""
  },
  {
    "Name": "Desarrollo Web Full-Stack",
    "Organization": "The Bridge",
    "Tech": "HTML,CSS,Javascript,Cypress,Firebase,Node.js,Express.js,MongoDB,SQL,Jest,React,Styled Components,hooks,Docker,Kubernetes,Jenkins",
    "Tags": "Full-stack",
    "Duration (hours)": "",
    "Duration (weeks)": "16,32",
    "Location": "Madrid,Remote",
    "Price": 7000,
    "type": "Full,Part-time",
    "language": "Spanish",
    "Notes": "",
    "URL": "",
    "Attachments": "Folleto Bootcamp FS 20Jul2021.pdf (https://dl.airtable.com/.attachments/d1d34abf9daab97bbd626af07822c6e1/b65f1f30/FolletoBootcampFS20Jul2021.pdf)"
  },
  {
    "Name": "Digital Marketing OPS",
    "Organization": "The Bridge",
    "Tech": "SEO,SEM,Retargeting,Social Networks,Inbound Marketing,CRO,Marketing automation,Data Analysis",
    "Tags": "Digital Marketing",
    "Duration (hours)": "",
    "Duration (weeks)": "16,32",
    "Location": "Madrid,Remote",
    "Price": 4950,
    "type": "Full,Part-time",
    "language": "Spanish",
    "Notes": "",
    "URL": "",
    "Attachments": "Folleto Bootcamp MKT 20Jul2021.pdf (https://dl.airtable.com/.attachments/ee3cee43921cc7f48cbccdc6ea078142/ba32cdac/FolletoBootcampMKT20Jul2021.pdf)"
  },
  {
    "Name": "UX/UI Product Design",
    "Organization": "The Bridge",
    "Tech": "HTML,CSS,Javascript,User Reseach,Customer Journey,Design Systems,UX,UI",
    "Tags": "UX/UI",
    "Duration (hours)": "",
    "Duration (weeks)": "16,32",
    "Location": "Madrid,Remote",
    "Price": 4950,
    "type": "Full,Part-time",
    "language": "Spanish",
    "Notes": "",
    "URL": "",
    "Attachments": "Folleto Bootcamp UX 20Jul2021.pdf (https://dl.airtable.com/.attachments/152926ba2b764e9d180b5a08f0b43981/3b68c92b/FolletoBootcampUX20Jul2021.pdf)"
  },
  {
    "Name": "Fullstack Web Developer: Opensource",
    "Organization": "Codehouse Academy",
    "Tech": "HTML,CSS,Bootstrap,SASS,Git,UX,UI,Javascript,typescript,Angular,BBDD,SQL,Node.js,Express.js",
    "Tags": "Full-stack",
    "Duration (hours)": "",
    "Duration (weeks)": 16,
    "Location": "Remote",
    "Price": 4200,
    "type": "Full,Part-time",
    "language": "Spanish",
    "Notes": "",
    "URL": "https://codehouse.academy/bootcamp-fullstack-web-developer-opensource/",
    "Attachments": ""
  },
  {
    "Name": "Fullstack Web Developer: .Net",
    "Organization": "Codehouse Academy",
    "Tech": "HTML,CSS,Bootstrap,SASS,Git,UX,UI,Javascript,typescript,Angular,BBDD,SQL,Node.js,Express.js,C#,SOLID,POO,.Net",
    "Tags": "Full-stack",
    "Duration (hours)": "",
    "Duration (weeks)": 16,
    "Location": "Remote",
    "Price": 4925,
    "type": "Full,Part-time",
    "language": "Spanish",
    "Notes": "",
    "URL": "https://codehouse.academy/bootcamp-fullstack-web-developer-net/",
    "Attachments": ""
  },
  {
    "Name": "Desarrollo Web y móvil",
    "Organization": "Codenotch",
    "Tech": "HTML,CSS,Javascript,Bootstrap,JQuery,SASS,Git,Node.js,Express.js,MongoDB,Angular,Ionic,Scrum,Kanban",
    "Tags": "Full-stack",
    "Duration (hours)": "",
    "Duration (weeks)": 12,
    "Location": "Madrid,Remote",
    "Price": 4500,
    "type": "Full",
    "language": "Spanish",
    "Notes": "",
    "URL": "https://www.codenotch.com/bootcamp-desarrollo-web-movil-full-time/",
    "Attachments": ""
  },
  {
    "Name": "Data Science - Full Time",
    "Organization": "Codenotch",
    "Tech": "Python,Jupyter,Spyder,Git,POO,SQL,MongoDB,Cassandra,BigData,Docker,Hadoop,MapReduce,Hive,PySpark,Kafka,NumPy,Pandas,Tableau,Data Visualization,Machine Learning,algorithms,Deep Learning",
    "Tags": "Data Science,Data Engineer",
    "Duration (hours)": "",
    "Duration (weeks)": 14,
    "Location": "Madrid,Remote",
    "Price": 4500,
    "type": "Full",
    "language": "Spanish",
    "Notes": "horario 17:00 - 21:00",
    "URL": "https://www.codenotch.com/bootcamp-data-science-full-time/",
    "Attachments": ""
  },
  {
    "Name": "Data Science - Part Time",
    "Organization": "Codenotch",
    "Tech": "Python,Jupyter,Spyder,Git,POO,SQL,MongoDB,Cassandra,BigData,Docker,Hadoop,MapReduce,Hive,PySpark,Kafka,NumPy,Pandas,Tableau,Data Visualization,Machine Learning,algorithms,Deep Learning",
    "Tags": "Data Science,Data Engineer",
    "Duration (hours)": "",
    "Duration (weeks)": 18,
    "Location": "Madrid,Remote",
    "Price": 4500,
    "type": "Part-time",
    "language": "Spanish",
    "Notes": "horario 9:30 - 16:30",
    "URL": "https://www.codenotch.com/bootcamp-data-science-full-time/",
    "Attachments": ""
  },
  {
    "Name": "UX/UI Design - Full Time",
    "Organization": "Neoland",
    "Tech": "UI,UX,User Reseach",
    "Tags": "UX/UI",
    "Duration (hours)": 480,
    "Duration (weeks)": 12,
    "Location": "Madrid,Remote",
    "Price": 4995,
    "type": "Full",
    "language": "Spanish",
    "Notes": "lunes a viernes de 09:00 a 18:00",
    "URL": "https://www.neoland.es/ux-design-bootcamp",
    "Attachments": ""
  },
  {
    "Name": "UX/UI Design - Part Time",
    "Organization": "Neoland",
    "Tech": "UI,UX,User Reseach",
    "Tags": "UX/UI",
    "Duration (hours)": 360,
    "Duration (weeks)": 36,
    "Location": "Remote",
    "Price": 3900,
    "type": "Part-time",
    "language": "Spanish",
    "Notes": "lunes a viernes de 19:00 a 21:00",
    "URL": "https://www.neoland.es/ux-design-bootcamp",
    "Attachments": ""
  },
  {
    "Name": "Full Stack - Full Time",
    "Organization": "Neoland",
    "Tech": "HTML,CSS,Javascript,React,Node.js,Express.js,MongoDB",
    "Tags": "Full-stack",
    "Duration (hours)": 480,
    "Duration (weeks)": 12,
    "Location": "Remote",
    "Price": 3995,
    "type": "Full",
    "language": "Spanish",
    "Notes": "horario de lunes a viernes de 09:00 a 18:00",
    "URL": "https://www.neoland.es/full-stack-bootcamp",
    "Attachments": ""
  },
  {
    "Name": "Full Stack - Part Time",
    "Organization": "Neoland",
    "Tech": "HTML,CSS,Javascript,React,Node.js,Express.js,MongoDB",
    "Tags": "Full-stack",
    "Duration (hours)": 360,
    "Duration (weeks)": 36,
    "Location": "Remote",
    "Price": 3990,
    "type": "Part-time",
    "language": "Spanish",
    "Notes": "lunes a viernes de 19:00 a 21:00",
    "URL": "https://www.neoland.es/full-stack-part-time-neoland",
    "Attachments": ""
  },
  {
    "Name": "Data Science - Full Time",
    "Organization": "Neoland",
    "Tech": "Python,Data Visualization,Data Analysis,Machine Learning,AI,Deep Learning",
    "Tags": "Data Science",
    "Duration (hours)": 480,
    "Duration (weeks)": 12,
    "Location": "Remote",
    "Price": 3995,
    "type": "Full",
    "language": "Spanish",
    "Notes": "horario de lunes a viernes de 09:00 a 18:00",
    "URL": "https://www.neoland.es/data-science-bootcamp",
    "Attachments": ""
  },
  {
    "Name": "Data Science - Part Time",
    "Organization": "Neoland",
    "Tech": "Python,Data Visualization,Data Analysis,Machine Learning,AI,Deep Learning",
    "Tags": "Data Science",
    "Duration (hours)": 360,
    "Duration (weeks)": 36,
    "Location": "Remote",
    "Price": 3995,
    "type": "Part-time",
    "language": "Spanish",
    "Notes": "lunes a viernes de 19:00 a 21:00",
    "URL": "https://www.neoland.es/data-science-part-time-neoland",
    "Attachments": ""
  },
  {
    "Name": "Cibersecurity - Full Time",
    "Organization": "Neoland",
    "Tech": "Red Team,Blue Team,Purple Team,Pentesting,OSINT,Networks,Javascript",
    "Tags": "Cybersecurity",
    "Duration (hours)": 480,
    "Duration (weeks)": 12,
    "Location": "Remote",
    "Price": 3995,
    "type": "Full",
    "language": "Spanish",
    "Notes": "horario de lunes a viernes de 09:00 a 18:00",
    "URL": "https://www.neoland.es/cybersecurity-bootcamp",
    "Attachments": "cybersecurity_bootcamp.pdf (https://dl.airtable.com/.attachments/0a2056aaf283a0867ba3506be3ab8201/a0c6da6a/cybersecurity_bootcamp.pdf)"
  },
  {
    "Name": "Cibersecurity - Part Time",
    "Organization": "Neoland",
    "Tech": "Red Team,Blue Team,Purple Team,Pentesting,OSINT,Networks,Javascript",
    "Tags": "Cybersecurity",
    "Duration (hours)": 360,
    "Duration (weeks)": 36,
    "Location": "Remote",
    "Price": 3900,
    "type": "Part-time",
    "language": "Spanish",
    "Notes": "lunes a viernes de 19:00 a 21:00",
    "URL": "https://www.neoland.es/cybersecurity-part-time",
    "Attachments": ""
  },
  {
    "Name": "Master in Software Development",
    "Organization": "Assembler School",
    "Tech": "HTML,CSS,Bootstrap,Javascript,React,Webpack,Jest,Redux,PHP,Laravel,POO,Node.js,MongoDB,Express.js",
    "Tags": "Full-stack",
    "Duration (hours)": 1200,
    "Duration (weeks)": 28,
    "Location": "Barcelona",
    "Price": "",
    "type": "Full",
    "language": "Spanish,English",
    "Notes": "Lun a Vie, 9am a 6pm. Se requieren conocimientos básicos de programación",
    "URL": "https://www.assemblerschool.com/home/full-stack-developer-program",
    "Attachments": ""
  },
  {
    "Name": "Adalab",
    "Organization": "Adalab",
    "Tech": "HTML,CSS,SASS,Bootstrap,Javascript,React,Git,Node.js,Express.js,SQL,VSCode,Linter,Zeplin",
    "Tags": "Full-stack",
    "Duration (hours)": "",
    "Duration (weeks)": 12,
    "Location": "Remote",
    "Price": 3990,
    "type": "Full",
    "language": "Spanish",
    "Notes": "Bootcamp para mujeres",
    "URL": "https://adalab.es/cursos-desarrollo-web/",
    "Attachments": ""
  },
  {
    "Name": "Programación y desarrollo web Full Stack",
    "Organization": "ID boot camps",
    "Tech": "HTML,CSS,Javascript,Angular,BBDD,Node.js",
    "Tags": "Full-stack",
    "Duration (hours)": 450,
    "Duration (weeks)": 12,
    "Location": "Madrid,Remote",
    "Price": 6100,
    "type": "Full",
    "language": "Spanish",
    "Notes": "L-J 9:00-18:00 V 9:00-14:30",
    "URL": "https://iddigitalschool.com/bootcamps/madrid/bootcamp-en-programacion-y-desarrollo-web-full-stack/",
    "Attachments": ""
  },
  {
    "Name": "Programación y desarrollo web Full Stack (part-time)",
    "Organization": "ID boot camps",
    "Tech": "HTML,CSS,Javascript,Angular,BBDD,Node.js",
    "Tags": "Full-stack",
    "Duration (hours)": 450,
    "Duration (weeks)": 36,
    "Location": "Madrid,Remote",
    "Price": 6100,
    "type": "Part-time",
    "language": "Spanish",
    "Notes": "Lunes a jueves 18:30-21:30",
    "URL": "https://iddigitalschool.com/bootcamps/madrid/bootcamp-en-programacion-y-desarrollo-web-full-stack/",
    "Attachments": ""
  },
  {
    "Name": "Data Science y Machine Learning",
    "Organization": "ID boot camps",
    "Tech": "Python,algorithms,BBDD,Web Scraping,API's,Data Visualization,Machine Learning,Deep Learning,NLP,BigData",
    "Tags": "Data Science",
    "Duration (hours)": 450,
    "Duration (weeks)": 12,
    "Location": "Madrid,Remote",
    "Price": 6100,
    "type": "Full",
    "language": "Spanish",
    "Notes": "L-J 9:00-18:00 V 9:00-14:30",
    "URL": "https://iddigitalschool.com/bootcamps/madrid/bootcamp-en-data-science-y-machine-learning/",
    "Attachments": ""
  },
  {
    "Name": "Data Science y Machine Learning (part-time)",
    "Organization": "ID boot camps",
    "Tech": "Python,algorithms,BBDD,Web Scraping,API's,Data Visualization,Machine Learning,Deep Learning,NLP,BigData",
    "Tags": "Data Science",
    "Duration (hours)": 450,
    "Duration (weeks)": 36,
    "Location": "Madrid,Remote",
    "Price": 6100,
    "type": "Part-time",
    "language": "Spanish",
    "Notes": "Lunes a jueves 18:30-21:30",
    "URL": "https://iddigitalschool.com/bootcamps/madrid/bootcamp-en-data-science-y-machine-learning/",
    "Attachments": ""
  },
  {
    "Name": "Ciberseguridad y Hacking Ético",
    "Organization": "ID boot camps",
    "Tech": "Networks,Linux,Red Team,Blue Team,Digital Forensics,Cybersecurity",
    "Tags": "Cybersecurity",
    "Duration (hours)": 450,
    "Duration (weeks)": 12,
    "Location": "Madrid,Remote",
    "Price": 6100,
    "type": "Full",
    "language": "Spanish",
    "Notes": "L-J 9:00-18:00 V 9:00-14:30",
    "URL": "https://iddigitalschool.com/bootcamps/madrid/bootcamp-en-ciberseguridad-y-hacking-etico/",
    "Attachments": ""
  },
  {
    "Name": "Ciberseguridad y Hacking Ético (part-time)",
    "Organization": "ID boot camps",
    "Tech": "Networks,Linux,Red Team,Blue Team,Digital Forensics,Cybersecurity",
    "Tags": "Cybersecurity",
    "Duration (hours)": 450,
    "Duration (weeks)": 36,
    "Location": "Madrid,Remote",
    "Price": 6100,
    "type": "Part-time",
    "language": "Spanish",
    "Notes": "Lunes a jueves 18:30-21:30",
    "URL": "https://iddigitalschool.com/bootcamps/madrid/bootcamp-en-ciberseguridad-y-hacking-etico/",
    "Attachments": ""
  },
  {
    "Name": "DevOps",
    "Organization": "ID boot camps",
    "Tech": "Git,GitFlow,AWS,Azure,Terraform,CloudFormation,Docker,Kubernetes,Ansible,Packer,CI/CD,Monitoring",
    "Tags": "SRE",
    "Duration (hours)": 450,
    "Duration (weeks)": 36,
    "Location": "Remote,Madrid",
    "Price": 6100,
    "type": "Part-time",
    "language": "Spanish",
    "Notes": "Lunes – Jueves de 18:30 a 21:30",
    "URL": "https://iddigitalschool.com/bootcamps/madrid/bootcamp-en-devops/",
    "Attachments": ""
  },
  {
    "Name": "Desarrollo de aplicaciones móviles (iOS, Android)",
    "Organization": "ID boot camps",
    "Tech": "Git,Scrum,Trello,Android,Android Studio,Xcode,Kotlin,Swift,UX,UI,Firebase",
    "Tags": "Mobile",
    "Duration (hours)": 450,
    "Duration (weeks)": 36,
    "Location": "Madrid,Remote",
    "Price": 6100,
    "type": "Part-time",
    "language": "Spanish",
    "Notes": "Lunes – Jueves de 18:30 a 21:30",
    "URL": "https://iddigitalschool.com/bootcamps/madrid/bootcamp-en-desarrollo-de-aplicaciones-moviles-ios-android/",
    "Attachments": ""
  },
  {
    "Name": "Diseño UX/UI y Product Management",
    "Organization": "ID boot camps",
    "Tech": "UX,UI,HTML,CSS,Flexbox,Scrum,Kanban,A/B Testing,CRO,VR,Digital Asistants",
    "Tags": "UX/UI",
    "Duration (hours)": 450,
    "Duration (weeks)": 36,
    "Location": "Madrid,Remote",
    "Price": 6100,
    "type": "Part-time",
    "language": "Spanish",
    "Notes": "Lunes – Jueves de 18:30 a 21:30",
    "URL": "https://iddigitalschool.com/bootcamps/madrid/bootcamp-en-diseno-ux-ui-y-product-management/",
    "Attachments": ""
  },
  {
    "Name": "Full-Stack Developer Bootcamp - Part Time",
    "Organization": "Upgrade HUB",
    "Tech": "HTML,CSS,Javascript,Node.js,Angular,React",
    "Tags": "Full-stack",
    "Duration (hours)": 320,
    "Duration (weeks)": "",
    "Location": "Madrid,Remote",
    "Price": 5900,
    "type": "Part-time",
    "language": "Spanish",
    "Notes": "Martes y Jueves de 18:30 a 22h | Sábados 8:30 a 15h",
    "URL": "https://www.upgrade-hub.com/landing-fullstack/?utm_source=google-search&utm_medium=cpc&utm_campaign=Search_MAD_FSD_Todos_GA-036&pkw=Bootcamp%20programacion&utm_term=Bootcamp%20programacion&matchtype=b&device=c&utm_content=508537898148&placement=&network=g&gclid=Cj0KCQjwm9yJBhDTARIsABKIcGZQHmPx3bbnFnwfEvGZgn8WKaVD1WdSZSB2J1Zy2wMGXXaxX_iqAkcaAjHiEALw_wcB",
    "Attachments": ""
  },
  {
    "Name": "Full-Stack Developer Bootcamp - Full Time",
    "Organization": "Upgrade HUB",
    "Tech": "HTML,CSS,Javascript,Node.js,Angular,React",
    "Tags": "Full-stack",
    "Duration (hours)": 320,
    "Duration (weeks)": "",
    "Location": "Madrid,Remote",
    "Price": 5900,
    "type": "Full",
    "language": "Spanish",
    "Notes": "Lunes a viernes 9h - 18h",
    "URL": "https://www.upgrade-hub.com/landing-fullstack/?utm_source=google-search&utm_medium=cpc&utm_campaign=Search_MAD_FSD_Todos_GA-036&pkw=Bootcamp%20programacion&utm_term=Bootcamp%20programacion&matchtype=b&device=c&utm_content=508537898148&placement=&network=g&gclid=Cj0KCQjwm9yJBhDTARIsABKIcGZQHmPx3bbnFnwfEvGZgn8WKaVD1WdSZSB2J1Zy2wMGXXaxX_iqAkcaAjHiEALw_wcB",
    "Attachments": ""
  },
  {
    "Name": "Ciberseguridad cloud y hacking ético - Part Time",
    "Organization": "Upgrade HUB",
    "Tech": "Networks,Linux,Cybersecurity,Cloud,OSINT,Hacking ético,Proxy,Firewall,Kali,metasploit,XG Firewall,Caine",
    "Tags": "Cybersecurity",
    "Duration (hours)": 180,
    "Duration (weeks)": "",
    "Location": "Madrid,Remote",
    "Price": 4900,
    "type": "Part-time",
    "language": "Spanish",
    "Notes": "Lunes, miércoles y viernes de 18:30 a 22h",
    "URL": "https://www.upgrade-hub.com/curso-ciberseguridad-informatica-hacking-part-time/",
    "Attachments": ""
  },
  {
    "Name": "Ciberseguridad cloud y hacking ético - Full Time",
    "Organization": "Upgrade HUB",
    "Tech": "Networks,Linux,Cybersecurity,Cloud,OSINT,Hacking ético,Proxy,Firewall,Kali,metasploit,XG Firewall,Caine",
    "Tags": "Cybersecurity",
    "Duration (hours)": 320,
    "Duration (weeks)": "",
    "Location": "Madrid,Remote",
    "Price": 5900,
    "type": "Full",
    "language": "Spanish",
    "Notes": "Lunes a viernes 9h - 18h",
    "URL": "https://www.upgrade-hub.com/curso-ciberseguridad-informatica-hacking-part-time/",
    "Attachments": ""
  }
]